[
  {
    "id": "p001",
    "category": "New Mobiles",
    "name": "iPhone 13 (128GB, Blue)",
    "price": 79999,
    "description": "Apple iPhone 13 with 128GB storage in stunning Blue color. Features A15 Bionic chip, dual-camera system, and Super Retina XDR display.",
    "image": "images/iphone13.jpg",
    "model": "3dmodels/iphone13.glb",
    "stock": 25,
    "rating": 4.7
  },
  {
    "id": "p002",
    "category": "Second Hand Mobiles",
    "name": "Samsung Galaxy S21 (8GB/128GB, Good condition)",
    "price": 35000,
    "description": "Used Samsung Galaxy S21 with 8GB RAM and 128GB storage, thoroughly tested and in good condition with minor signs of usage.",
    "image": "images/galaxys21.jpg",
    "model": "3dmodels/galaxys21.glb",
    "stock": 10,
    "rating": 4.2
  },
  {
    "id": "p003",
    "category": "Accessories",
    "name": "Premium Shockproof Case for iPhone 13",
    "price": 1299,
    "description": "Durable and stylish shockproof case designed specifically for iPhone 13. Provides excellent protection without adding bulk.",
    "image": "images/iphone13case.jpg",
    "model": "",
    "stock": 100,
    "rating": 4.8
  }
]
